pytools/__init__.py
pytools/pytools.py
pytools_asxgxr-0.1.0.dist-info/LICENSE
pytools_asxgxr-0.1.0.dist-info/METADATA
pytools_asxgxr-0.1.0.dist-info/WHEEL
pytools_asxgxr-0.1.0.dist-info/top_level.txt
pytools_asxgxr-0.1.0.dist-info/RECORD
